<PAMDataset>
  <PAMRasterBand band="1">
    <Metadata>
      <MDI key="STATISTICS_MAXIMUM">255</MDI>
      <MDI key="STATISTICS_MEAN">55.774556291391</MDI>
      <MDI key="STATISTICS_MINIMUM">0</MDI>
      <MDI key="STATISTICS_STDDEV">101.3555560295</MDI>
      <MDI key="STATISTICS_VALID_PERCENT">100</MDI>
    </Metadata>
  </PAMRasterBand>
  <PAMRasterBand band="2">
    <Metadata>
      <MDI key="STATISTICS_MAXIMUM">255</MDI>
      <MDI key="STATISTICS_MEAN">54.357231788079</MDI>
      <MDI key="STATISTICS_MINIMUM">0</MDI>
      <MDI key="STATISTICS_STDDEV">98.643633273768</MDI>
      <MDI key="STATISTICS_VALID_PERCENT">100</MDI>
    </Metadata>
  </PAMRasterBand>
  <PAMRasterBand band="3">
    <Metadata>
      <MDI key="STATISTICS_MAXIMUM">191</MDI>
      <MDI key="STATISTICS_MEAN">39.426145695364</MDI>
      <MDI key="STATISTICS_MINIMUM">0</MDI>
      <MDI key="STATISTICS_STDDEV">72.04569716032</MDI>
      <MDI key="STATISTICS_VALID_PERCENT">100</MDI>
    </Metadata>
  </PAMRasterBand>
</PAMDataset>
